pymongoimport
test
