Metadata-Version: 1.2
Name: pymongoimport
Version: 1.5.5
Summary: pymongoimport - a program for reading CSV files into mongodb
Home-page: https://github.com/jdrumgoole/pymongoimport
Author: Joe Drumgoole
Author-email: joe@joedrumgoole.com
License: AGPL
Keywords: MongoDB import csv tsv
Platform: UNKNOWN
Classifier: Development Status :: 3 - Alpha
Classifier: Intended Audience :: Developers
Classifier: License :: OSI Approved :: GNU Affero General Public License v3
Classifier: Programming Language :: Python :: 3.7
Requires-Python: >3.7
